file_replace_helper/__init__.py
file_replace_helper/file_utils.py
file_replace_helper/pattern_replace_helper.py
file_replace_helper/pattern_replacer.py
file_replace_helper-0.0.3.dist-info/METADATA
file_replace_helper-0.0.3.dist-info/WHEEL
file_replace_helper-0.0.3.dist-info/top_level.txt
file_replace_helper-0.0.3.dist-info/RECORD
