Metadata-Version: 2.1
Name: file-replace-helper
Version: 0.0.3
Summary: A small example package to help manipulate files through regex and other file utils
Home-page: https://github.com/pypa/sampleproject
Author: Madhavth
Author-email: powermt2012@gmail.com
License: UNKNOWN
Project-URL: Bug Tracker, https://github.com/pypa/sampleproject/issues
Platform: UNKNOWN
Classifier: Programming Language :: Python :: 3
Classifier: License :: OSI Approved :: MIT License
Classifier: Operating System :: OS Independent
Requires-Python: >=3.6
